mkdocs_macros_utils/__init__.py
mkdocs_macros_utils/debug_logger.py
mkdocs_macros_utils/gist_codeblock.py
mkdocs_macros_utils/link_card.py
mkdocs_macros_utils/static/css/gist-cb.css
mkdocs_macros_utils/static/css/link-card.css
mkdocs_macros_utils/static/css/x-twitter-link-card.css
mkdocs_macros_utils/static/js/x-twitter-widget.js
mkdocs_macros_utils/x_twitter_card.py
mkdocs_macros_utils-0.0.8.dist-info/LICENCE
mkdocs_macros_utils-0.0.8.dist-info/METADATA
mkdocs_macros_utils-0.0.8.dist-info/WHEEL
mkdocs_macros_utils-0.0.8.dist-info/RECORD
