Metadata-Version: 2.3
Name: mkdocs-macros-utils
Version: 0.0.8
Summary: mkdocs-macros-utils is a mkdocs-macros-plugin based project that provides macros to extend cards, code blocks, etc, in MkDocs documents.
Author: 7rikazhexde
Author-email: 33836132+7rikazhexde@users.noreply.github.com
Requires-Python: >=3.10,<4.0
Classifier: Programming Language :: Python :: 3
Classifier: Programming Language :: Python :: 3.10
Classifier: Programming Language :: Python :: 3.11
Classifier: Programming Language :: Python :: 3.12
Classifier: Programming Language :: Python :: 3.13
Requires-Dist: jinja2 (>=3.0.0)
Requires-Dist: mkdocs-macros-plugin (>=1.3.7,<2.0.0)
Requires-Dist: mkdocs-material (>=9.6.1,<10.0.0)
Requires-Dist: pygments (>=2.19.1)
Requires-Dist: requests (>=2.25.0)
Project-URL: Documentation, https://7rikazhexde.github.io/mkdocs-macros-utils/
Project-URL: Homepage, https://github.com/7rikazhexde/mkdocs-macros-utils
Project-URL: Repository, https://github.com/7rikazhexde/mkdocs-macros-utils
